Workbook

Sheet Findings
B1: Jackrabbit Class List — Reconciliation Findings
B2: Source: ClassesListReport.xls · 176 classes · exported 28 July 2026
B4: HEADLINE
C5: The categories DO support your nine service rows — with two structural exceptions you need to decide on.
C6: But this export contains NO 2023, 2024 or 2025 classes. It is the current session only.
B8: 1. Category 1 separates Rec from Team cleanly
C9: Recreational 155 · Team 18 · Staff 3. My earlier read off your screenshot was wrong — Cat1 is not
C10: uniformly 'Recreational'. It does carry the top-level split.
B12: 2. Category 2 is the service-level key
C13: Rec Girls 86 · Pre-School 36 · Rec Boys 12 · Tumble (Combined) 12 · Parent-Child 9 · blank 21.
C14: These map onto four of your rows with no ambiguity. Parent-Child (First Flight) folds into Preschool.
C15: The 21 blanks are exactly the 18 Team + 3 Staff classes — Team carries no Cat2 or Cat3 at all.
B17: 3. TEAM IS DOUBLE-ENROLLED BY DESIGN — the important one
C18: Only 7 of the 18 Team classes carry tuition. They are hour-tier billing groups:
C19: 1 Day $255 · 6 hrs $310 · 2 days $350 · 9 hrs $385 · 12 hr $440 · 16 hrs $485 · 20 hrs $543
C20: The other 11 are $0 containers — 'MAG Team 2026-27' (77 enrolled) plus practice groups (Xcel Silver/Gold/
C21: Platinum/Diamond, WDP L3/L4/Optionals, Mens Devo, Womens Devo).
C22: Team athletes sit in a billing group AND a practice group AND the roster. Summing enrollment across all 18
C23: would triple-count them. Team revenue = the 7 billing groups only (74 enrolled). Use practice groups for
C24: headcount and level mix, never for revenue.
C25: Consequence: you CANNOT split team revenue girls vs boys. Billing groups are gender-blind. Headcount can be
C26: inferred (Mens Devo 13 vs everything else) but the dollars cannot.
B28: 4. Pre-Team barely exists as a service line
C29: Only 2 classes are tagged PT in Cat3: 'Hot Shots' (Girls PT1, 9 enrolled, $310) and 'Boys Advanced 2 hr'
C30: (Boys PT2, 1 enrolled, $200). Both sit under Rec Girls / Rec Boys in Cat2, so I applied a Cat3 override.
C31: 10 students total. Consider folding this row into the rec rows — it will not carry a meaningful trend.
B33: 5. Summer Intensives are a separate product priced differently
C34: 11 classes in '2026 Summer Intensive' — the website's Summer Mini-Sessions. Flat 6-week fees ($183–$300),
C35: not monthly tuition. They carry the same Cat2 values as the year-round classes, so they will blend into
C36: your rec rows and distort Avg. Transaction Value unless separated. Flagged 'OK - summer session'.
B38: 6. Thirty-six classes carry $0 tuition
C39: 22 Recreational · 11 Team · 3 Staff. Waitlists, roster containers, practice groups and staff
C40: placeholders. Excluded from pricing via the 'Billable' column so they do not drag the averages to zero.
B42: 7. NO HISTORICAL DATA IN THIS EXPORT
C43: Session mix: 2026-27 Rec 144 · 2026-27 Team 18 · 2026 Summer Intensive 11 · 2025-26 Rec 1 · blank 2.
C44: There is not a single 2023, 2024 or 2025 class here. This file gives you current price and current
C45: enrollment — nothing for the three-year comparison.
C46: The 2023–2025 numbers must come from the revenue and transaction reports filtered by date range, not from
C47: the class list. Re-run the class list with archived sessions included if you also want historical prices.
B49: 8. Fill rate — a genuine finding, available right now
C50: Tumbling 81.6% · Preschool 77.0% · Rec Girls 69.8% · Parent-Child 58.3% · Rec Boys 51.5%
C51: Rec Boys is running about half empty across 12 classes. Since coach cost is fixed once a class runs, those
C52: empty seats are pure lost margin — likely the single highest-leverage item in the whole analysis.
B54: WHAT I NEED FROM YOU NEXT
C55: a) Decide: keep Pre-Team as its own row, or fold into rec?
C56: b) Decide: Summer Intensives as their own row, or blended into the rec rows?
C57: c) Pull the revenue reports for calendar 2023, 2024 and 2025 (Revenue Summary or Class/Event Revenue),
C58: on a consistent basis (billed or collected), so I can fill the three-year sheet.

Sheet Class Export (mapped)
B1: Class Export — mapped to service rows
B4: Class | C4: Cat1 | D4: Cat2 | E4: Cat3 | F4: Session | G4: Status | H4: Instructors | I4: Days | J4: Start Time | K4: Duration | L4: Tuition | M4: Enrolled | N4: Max | O4: Cat Key | P4: Maps To | Q4: Billable | R4: Flag
B5: MAG Team 2026-27 | C5: Team | F5: 2026-27 Team | G5: Active | H5: Jamian W., Susan W., Rigel (Jonathan) L. | J5: 12:00am | K5: 12:00 | L5: 0 | M5: 77 | N5: 100 | O5: Team | (blank) | P5: Competitive -- American Flyers Teams | Q5: No | R5: TEAM PRACTICE GRP - $0
B6: Team 26-27 Xcel Gold 1 Practice Group | C6: Team | F6: 2026-27 Team | G6: Active | H6: Susan W., Rigel (Jonathan) L., Riley P., Maya L. | I6: TuThSu | L6: 0 | M6: 7 | N6: 10 | O6: Team | (blank) | P6: Competitive -- American Flyers Teams | Q6: No | R6: TEAM PRACTICE GRP - $0
B7: Team 26-27 Xcel Platinum2/Diamond Practice Group | C7: Team | F7: 2026-27 Team | G7: Active | H7: Susan W., Rigel (Jonathan) L., Kyla P., Jamian W. | I7: MTuWSu | L7: 0 | M7: 8 | N7: 10 | O7: Team | (blank) | P7: Competitive -- American Flyers Teams | Q7: No | R7: TEAM PRACTICE GRP - $0
B8: Team 26-27 Billing Group 1 Day | C8: Team | F8: 2026-27 Team | G8: Active | L8: 255 | M8: 1 | N8: 20 | O8: Team | (blank) | P8: Competitive -- American Flyers Teams | Q8: Yes | R8: OK
B9: Team 26-27 Billing Group 12hr | C9: Team | F9: 2026-27 Team | G9: Active | L9: 440 | M9: 25 | N9: 40 | O9: Team | (blank) | P9: Competitive -- American Flyers Teams | Q9: Yes | R9: OK
B10: Team 26-27 Billing Group 16hrs | C10: Team | F10: 2026-27 Team | G10: Active | L10: 485 | M10: 17 | N10: 30 | O10: Team | (blank) | P10: Competitive -- American Flyers Teams | Q10: Yes | R10: OK
B11: Team 26-27 Billing Group 2 days | C11: Team | F11: 2026-27 Team | G11: Active | L11: 350 | M11: 4 | N11: 20 | O11: Team | (blank) | P11: Competitive -- American Flyers Teams | Q11: Yes | R11: OK
B12: Team 26-27 Billing Group 20 hrs | C12: Team | F12: 2026-27 Team | G12: Active | L12: 543 | M12: 12 | N12: 15 | O12: Team | (blank) | P12: Competitive -- American Flyers Teams | Q12: Yes | R12: OK
B13: Team 26-27 Billing Group 6 hrs | C13: Team | F13: 2026-27 Team | G13: Active | L13: 310 | M13: 8 | N13: 20 | O13: Team | (blank) | P13: Competitive -- American Flyers Teams | Q13: Yes | R13: OK
B14: Team 26-27 Billing Group 9 hrs | C14: Team | F14: 2026-27 Team | G14: Active | L14: 385 | M14: 7 | N14: 20 | O14: Team | (blank) | P14: Competitive -- American Flyers Teams | Q14: Yes | R14: OK
B15: Team 26-27 Mens Devo | C15: Team | F15: 2026-27 Team | G15: Active | H15: Rigel (Jonathan) L., Jamian W., Ryan A. | I15: MTuWThFSaSu | J15: 3:30pm | K15: 4:00 | L15: 0 | M15: 13 | N15: 20 | O15: Team | (blank) | P15: Competitive -- American Flyers Teams | Q15: No | R15: TEAM PRACTICE GRP - $0
B16: Team 26-27 WDP L3 | C16: Team | F16: 2026-27 Team | G16: Active | H16: Denae C., Jamian W., Alexa A., Kyla P. | I16: TuThSa | L16: 0 | M16: 5 | N16: 20 | O16: Team | (blank) | P16: Competitive -- American Flyers Teams | Q16: No | R16: TEAM PRACTICE GRP - $0
B17: Team 26-27 WDP L4 | C17: Team | F17: 2026-27 Team | G17: Active | H17: Jamian W., Denae C., Alexa A., Kyla P. | I17: TuThSa | L17: 0 | M17: 9 | N17: 46 | O17: Team | (blank) | P17: Competitive -- American Flyers Teams | Q17: No | R17: TEAM PRACTICE GRP - $0
B18: Team 26-27 WDP Optionals | C18: Team | F18: 2026-27 Team | G18: Active | H18: Alexa A., Jamian W., Denae C. | I18: MTuWThSa | J18: 2:45pm | K18: 4:00 | L18: 0 | M18: 17 | N18: 25 | O18: Team | (blank) | P18: Competitive -- American Flyers Teams | Q18: No | R18: TEAM PRACTICE GRP - $0
B19: Team 26-27 Womens Devo | C19: Team | F19: 2026-27 Team | G19: Active | H19: Jamian W., Denae C., Alexa A., Kyla P. | L19: 0 | M19: 33 | N19: 50 | O19: Team | (blank) | P19: Competitive -- American Flyers Teams | Q19: No | R19: TEAM PRACTICE GRP - $0
B20: Team 26-27 Xcel | C20: Team | F20: 2026-27 Team | G20: Active | H20: Susan W., Jamian W., Kyla P., Rigel (Jonathan) L. | L20: 0 | M20: 31 | N20: 40 | O20: Team | (blank) | P20: Competitive -- American Flyers Teams | Q20: No | R20: TEAM PRACTICE GRP - $0
B21: Team 26-27 Xcel Gold2/Platinum 1 Practice Group | C21: Team | F21: 2026-27 Team | G21: Active | H21: Susan W., Rigel (Jonathan) L., Kyla P., Jamian W. | I21: MWSu | L21: 0 | M21: 9 | N21: 11 | O21: Team | (blank) | P21: Competitive -- American Flyers Teams | Q21: No | R21: TEAM PRACTICE GRP - $0
B22: Team 26-27 Xcel Silver Practice Group | C22: Team | F22: 2026-27 Team | G22: Active | H22: Susan W., Rigel (Jonathan) L., Jamian W., Kyla P. | I22: TuThSu | L22: 0 | M22: 5 | N22: 20 | O22: Team | (blank) | P22: Competitive -- American Flyers Teams | Q22: No | R22: TEAM PRACTICE GRP - $0
B23: Boys Advanced 2 hr | C23: Recreational | D23: Rec Boys | E23: Boys PT2 | F23: 2026-27 Rec | G23: Active | H23: Nyx W., MAG A. | J23: 5:30pm | K23: 2:00 | L23: 200 | M23: 1 | N23: 2 | O23: Recreational | Rec Boys | P23: Competitive -- Pre-Team | Q23: Yes | R23: OK
B24: Hot Shots | C24: Recreational | D24: Rec Girls | E24: Girls PT1 | F24: 2026-27 Rec | G24: Active | H24: Kyla P., Riley P., Jamian W., MAG A. | I24: MW | J24: 3:30pm | K24: 3:00 | L24: 310 | M24: 9 | N24: 10 | O24: Recreational | Rec Girls | P24: Competitive -- Pre-Team | Q24: Yes | R24: OK
B25: MAG STAFF | C25: Staff | F25: 2025-26 Rec | G25: Active | H25: Alexa A., Jamian W., Nicole E., Lisa (Alyssa) A. | I25: MTuWThFSaSu | L25: 0 | M25: 24 | N25: 150 | O25: Staff | (blank) | P25: EXCLUDE -- Staff placeholder | Q25: No | R25: EXCLUDED - not revenue
B26: Tuesday Staff | C26: Staff | G26: On Hold | H26: Jamian W. | I26: Tu | J26: 8:30am | K26: 12:00 | L26: 0 | M26: 0 | N26: 20 | O26: Staff | (blank) | P26: EXCLUDE -- Staff placeholder | Q26: No | R26: EXCLUDED - not revenue
B27: Wednesday Staff | C27: Staff | G27: On Hold | H27: Jamian W. | I27: W | J27: 8:30am | K27: 12:00 | L27: 0 | M27: 0 | N27: 20 | O27: Staff | (blank) | P27: EXCLUDE -- Staff placeholder | Q27: No | R27: EXCLUDED - not revenue
B28: Boys Red Wings M 3:45p | C28: Recreational | D28: Rec Boys | E28: Boys B1 | F28: 2026-27 Rec | G28: Active | H28: Abram K., MAG A. | I28: M | J28: 3:45pm | K28: 1:15 | L28: 143 | M28: 8 | N28: 8 | O28: Recreational | Rec Boys | P28: Recreational -- Boys Wings | Q28: Yes | R28: OK
B29: Boys Red Wings F 4:15p (5-7yrs) | C29: Recreational | D29: Rec Boys | E29: Boys B1 | F29: 2026-27 Rec | G29: Active | H29: Michael K., MAG A. | I29: F | J29: 4:15pm | K29: 1:15 | L29: 143 | M29: 3 | N29: 8 | O29: Recreational | Rec Boys | P29: Recreational -- Boys Wings | Q29: Yes | R29: OK
B30: Boys Red Wings F 5:45p | C30: Recreational | D30: Rec Boys | E30: Boys B1 | F30: 2026-27 Rec | G30: Active | H30: Michael K., MAG A. | I30: F | J30: 5:45pm | K30: 1:15 | L30: 143 | M30: 2 | N30: 8 | O30: Recreational | Rec Boys | P30: Recreational -- Boys Wings | Q30: Yes | R30: OK
B31: Boys Red Wings W 4:00p | C31: Recreational | D31: Rec Boys | E31: Boys B1 | F31: 2026-27 Rec | G31: Active | H31: Michael K., MAG A. | I31: W | J31: 4:00pm | K31: 1:15 | L31: 143 | M31: 3 | N31: 8 | O31: Recreational | Rec Boys | P31: Recreational -- Boys Wings | Q31: Yes | R31: OK
B32: Boys Red Wings W 5:30p | C32: Recreational | D32: Rec Boys | E32: Boys B1 | F32: 2026-27 Rec | G32: Active | H32: Michael K., MAG A. | I32: W | J32: 5:30pm | K32: 1:15 | L32: 143 | M32: 5 | N32: 8 | O32: Recreational | Rec Boys | P32: Recreational -- Boys Wings | Q32: Yes | R32: OK
B33: Boys Red Wings Waitlist | C33: Recreational | D33: Rec Boys | E33: Boys B1 | F33: 2026-27 Rec | G33: Active | L33: 0 | M33: 0 | N33: 0 | O33: Recreational | Rec Boys | P33: Recreational -- Boys Wings | Q33: No | R33: NO TUITION
B34: Boys Red Wings Waitlist-Level Adjustment | C34: Recreational | D34: Rec Boys | E34: Boys B1 | F34: 2026-27 Rec | G34: Active | L34: 0 | M34: 0 | N34: 0 | O34: Recreational | Rec Boys | P34: Recreational -- Boys Wings | Q34: No | R34: NO TUITION
B35: Boys White Wings Waitlist - Level Adjustment | C35: Recreational | D35: Rec Boys | E35: Boys B2 | F35: 2026-27 Rec | G35: Active | L35: 0 | M35: 0 | N35: 0 | O35: Recreational | Rec Boys | P35: Recreational -- Boys Wings | Q35: No | R35: NO TUITION
B36: Boys White Wings F 3:45p | C36: Recreational | D36: Rec Boys | E36: Boys B2 | F36: 2026-27 Rec | G36: Active | H36: Nyx W., MAG A. | I36: F | J36: 3:45pm | K36: 1:30 | L36: 167 | M36: 6 | N36: 8 | O36: Recreational | Rec Boys | P36: Recreational -- Boys Wings | Q36: Yes | R36: OK
B37: Boys White Wings Su 11:30a Starts 9/13 | C37: Recreational | D37: Rec Boys | E37: Boys B2 | F37: 2026-27 Rec | G37: Active | H37: Nyx W., MAG A. | I37: Su | J37: 11:30am | K37: 1:30 | L37: 167 | M37: 4 | N37: 8 | O37: Recreational | Rec Boys | P37: Recreational -- Boys Wings | Q37: Yes | R37: OK
B38: Summer 2026 Boys White Wings W 3:45 - 6 weeks | C38: Recreational | D38: Rec Boys | E38: Boys B2 | F38: 2026 Summer Intensive | G38: Active | H38: Kjeld N., MAG A. | I38: W | J38: 3:45pm | K38: 1:30 | L38: 250.5 | M38: 2 | N38: 8 | O38: Recreational | Rec Boys | P38: Recreational -- Boys Wings | Q38: Yes | R38: OK - summer session
B39: Kinder Red Wings M 3:45p | C39: Recreational | D39: Rec Girls | E39: Girls G1 | F39: 2026-27 Rec | G39: Active | H39: Faith F., MAG A. | I39: M | J39: 3:45pm | K39: 1:15 | L39: 143 | M39: 8 | N39: 8 | O39: Recreational | Rec Girls | P39: Recreational -- Girls Wings | Q39: Yes | R39: OK
B40: Kinder Red Wings M 5:00p | C40: Recreational | D40: Rec Girls | E40: Girls G1 | F40: 2026-27 Rec | G40: Active | H40: Ruthie G., MAG A. | I40: M | J40: 5:00pm | K40: 1:15 | L40: 143 | M40: 6 | N40: 8 | O40: Recreational | Rec Girls | P40: Recreational -- Girls Wings | Q40: Yes | R40: OK
B41: Kinder Red Wings S 11:45a starts 9/12 | C41: Recreational | D41: Rec Girls | E41: Girls G1 | F41: 2026-27 Rec | G41: Active | H41: Amelia K., MAG A. | I41: Sa | J41: 11:45am | K41: 1:15 | L41: 143 | M41: 7 | N41: 8 | O41: Recreational | Rec Girls | P41: Recreational -- Girls Wings | Q41: Yes | R41: OK
B42: Kinder Red Wings Su 3:00p starts 9/13 | C42: Recreational | D42: Rec Girls | E42: Girls G1 | F42: 2026-27 Rec | G42: Active | H42: Faith F., MAG A. | I42: Su | J42: 3:00pm | K42: 1:15 | L42: 143 | M42: 7 | N42: 8 | O42: Recreational | Rec Girls | P42: Recreational -- Girls Wings | Q42: Yes | R42: OK
B43: Kinder Red Wings T 3:45p | C43: Recreational | D43: Rec Girls | E43: Girls G1 | F43: 2026-27 Rec | G43: Active | H43: Danica C., MAG A. | I43: Tu | J43: 3:45pm | K43: 1:15 | L43: 143 | M43: 8 | N43: 8 | O43: Recreational | Rec Girls | P43: Recreational -- Girls Wings | Q43: Yes | R43: OK
B44: Kinder Red Wings Th 3:45p | C44: Recreational | D44: Rec Girls | E44: Girls G1 | F44: 2026-27 Rec | G44: Active | H44: Claire S., MAG A. | I44: Th | J44: 3:45pm | K44: 1:15 | L44: 143 | M44: 4 | N44: 8 | O44: Recreational | Rec Girls | P44: Recreational -- Girls Wings | Q44: Yes | R44: OK
B45: Kinder Red Wings W 3:45p | C45: Recreational | D45: Rec Girls | E45: Girls G1 | F45: 2026-27 Rec | G45: Active | H45: Faith F., MAG A. | I45: W | J45: 3:45pm | K45: 1:15 | L45: 143 | M45: 7 | N45: 8 | O45: Recreational | Rec Girls | P45: Recreational -- Girls Wings | Q45: Yes | R45: OK
B46: Kinder Red Wings/Beginner W 5:00p | C46: Recreational | D46: Rec Girls | E46: Girls G1 | F46: 2026-27 Rec | G46: Active | H46: Faith F., MAG A. | I46: W | J46: 5:00pm | K46: 1:15 | L46: 143 | M46: 4 | N46: 8 | O46: Recreational | Rec Girls | P46: Recreational -- Girls Wings | Q46: Yes | R46: OK
B47: Kinder Red Wings/Beginner Waitlist (Kindergarten) | C47: Recreational | D47: Rec Girls | E47: Girls G1 | F47: 2026-27 Rec | G47: Active | L47: 0 | M47: 0 | N47: 0 | O47: Recreational | Rec Girls | P47: Recreational -- Girls Wings | Q47: No | R47: NO TUITION
B48: Kinder Red Wings/Beginner Waitlist (Kindergarten) -Level Adjustment | C48: Recreational | D48: Rec Girls | E48: Girls G1 | F48: 2026-27 Rec | G48: Active | L48: 0 | M48: 0 | N48: 0 | O48: Recreational | Rec Girls | P48: Recreational -- Girls Wings | Q48: No | R48: NO TUITION
B49: Red Wings/Beginner Waitlist (6-8yrs) | C49: Recreational | D49: Rec Girls | E49: Girls G1 | F49: 2026-27 Rec | G49: Active | L49: 0 | M49: 0 | N49: 0 | O49: Recreational | Rec Girls | P49: Recreational -- Girls Wings | Q49: No | R49: NO TUITION
B50: Red Wings/Beginner F 4:00p | C50: Recreational | D50: Rec Girls | E50: Girls G1 | F50: 2026-27 Rec | G50: Active | H50: Mila T., MAG A. | I50: F | J50: 4:00pm | K50: 1:15 | L50: 143 | M50: 3 | N50: 8 | O50: Recreational | Rec Girls | P50: Recreational -- Girls Wings | Q50: Yes | R50: OK
B51: Red Wings/Beginner F 5:30p | C51: Recreational | D51: Rec Girls | E51: Girls G1 | F51: 2026-27 Rec | G51: Active | H51: Kjeld N., MAG A. | I51: F | J51: 5:30pm | K51: 1:15 | L51: 143 | M51: 3 | N51: 8 | O51: Recreational | Rec Girls | P51: Recreational -- Girls Wings | Q51: Yes | R51: OK
B52: Red Wings/Beginner M 3:45p | C52: Recreational | D52: Rec Girls | E52: Girls G1 | F52: 2026-27 Rec | G52: Active | H52: Nicole E., MAG A. | I52: M | J52: 3:45pm | K52: 1:15 | L52: 143 | M52: 6 | N52: 8 | O52: Recreational | Rec Girls | P52: Recreational -- Girls Wings | Q52: Yes | R52: OK
B53: Red Wings/Beginner M 5:00p | C53: Recreational | D53: Rec Girls | E53: Girls G1 | F53: 2026-27 Rec | G53: Active | H53: Niamh M., MAG A. | I53: M | J53: 5:00pm | K53: 1:15 | L53: 143 | M53: 5 | N53: 8 | O53: Recreational | Rec Girls | P53: Recreational -- Girls Wings | Q53: Yes | R53: OK
B54: Red Wings/Beginner S 11:45a (6-8yrs) Starts 9/12 | C54: Recreational | D54: Rec Girls | E54: Girls G1 | F54: 2026-27 Rec | G54: Active | H54: Claire S., MAG A. | I54: Sa | J54: 11:45am | K54: 1:15 | L54: 143 | M54: 8 | N54: 8 | O54: Recreational | Rec Girls | P54: Recreational -- Girls Wings | Q54: Yes | R54: OK
B55: Red Wings/Beginner S 1:00p (6-8yrs) Starts 9/12 | C55: Recreational | D55: Rec Girls | E55: Girls G1 | F55: 2026-27 Rec | G55: Active | H55: Amelia K., MAG A. | I55: Sa | J55: 1:00pm | K55: 1:15 | L55: 143 | M55: 6 | N55: 8 | O55: Recreational | Rec Girls | P55: Recreational -- Girls Wings | Q55: Yes | R55: OK
B56: Red Wings/Beginner T 3:45p (6-8yrs) | C56: Recreational | D56: Rec Girls | E56: Girls G1 | F56: 2026-27 Rec | G56: Active | H56: Riley C., MAG A. | I56: Tu | J56: 3:45pm | K56: 1:15 | L56: 143 | M56: 2 | N56: 8 | O56: Recreational | Rec Girls | P56: Recreational -- Girls Wings | Q56: Yes | R56: OK
B57: Red Wings/Beginner T 5:15p | C57: Recreational | D57: Rec Girls | E57: Girls G1 | F57: 2026-27 Rec | G57: Active | H57: Kate P., MAG A. | I57: Tu | J57: 5:15pm | K57: 1:15 | L57: 143 | M57: 8 | N57: 8 | O57: Recreational | Rec Girls | P57: Recreational -- Girls Wings | Q57: Yes | R57: OK
B58: Red Wings/Beginner Th 3:45p (6-8yrs) | C58: Recreational | D58: Rec Girls | E58: Girls G1 | F58: 2026-27 Rec | G58: Active | H58: Danica C., MAG A. | I58: Th | J58: 3:45pm | K58: 1:15 | L58: 143 | M58: 4 | N58: 8 | O58: Recreational | Rec Girls | P58: Recreational -- Girls Wings | Q58: Yes | R58: OK
B59: Red Wings/Beginner Th 5:00p (6-8yrs) | C59: Recreational | D59: Rec Girls | E59: Girls G1 | F59: 2026-27 Rec | G59: Active | H59: Danica C., MAG A. | I59: Th | J59: 5:00pm | K59: 1:15 | L59: 143 | M59: 6 | N59: 8 | O59: Recreational | Rec Girls | P59: Recreational -- Girls Wings | Q59: Yes | R59: OK
B60: Red Wings/Beginner W 3:45p | C60: Recreational | D60: Rec Girls | E60: Girls G1 | F60: 2026-27 Rec | G60: Active | H60: Kaylee H., MAG A. | I60: W | J60: 3:45pm | K60: 1:15 | L60: 143 | M60: 5 | N60: 8 | O60: Recreational | Rec Girls | P60: Recreational -- Girls Wings | Q60: Yes | R60: OK
B61: Red Wings/Beginner W 5:00p | C61: Recreational | D61: Rec Girls | E61: Girls G1 | F61: 2026-27 Rec | G61: Active | H61: Kaylee H., MAG A. | I61: W | J61: 5:00pm | K61: 1:15 | L61: 143 | M61: 5 | N61: 8 | O61: Recreational | Rec Girls | P61: Recreational -- Girls Wings | Q61: Yes | R61: OK
B62: Red Wings/Beginner Waitlist (6-8yrs)-Level Adjustment | C62: Recreational | D62: Rec Girls | E62: Girls G1 | F62: 2026-27 Rec | G62: Active | L62: 0 | M62: 0 | N62: 0 | O62: Recreational | Rec Girls | P62: Recreational -- Girls Wings | Q62: No | R62: NO TUITION
B63: Red Wings/Beginner Waitlist (8+yrs) | C63: Recreational | D63: Rec Girls | E63: Girls G1 | F63: 2026-27 Rec | G63: Active | K63: 1:15 | L63: 0 | M63: 0 | N63: 0 | O63: Recreational | Rec Girls | P63: Recreational -- Girls Wings | Q63: No | R63: NO TUITION
B64: Summer 2026 Red Wings Intensive Th 3:45p - 6 weeks | C64: Recreational | D64: Rec Girls | E64: Girls G1 | F64: 2026 Summer Intensive | G64: Active | H64: Joelle R., MAG A. | I64: Th | J64: 3:45pm | K64: 1:15 | L64: 214.5 | M64: 2 | N64: 8 | O64: Recreational | Rec Girls | P64: Recreational -- Girls Wings | Q64: Yes | R64: OK - summer session
B65: Summer 2026 Red Wings Intensive Th 5:00p - 6 weeks | C65: Recreational | D65: Rec Girls | E65: Girls G1 | F65: 2026 Summer Intensive | G65: Active | H65: Joelle R., MAG A. | I65: Th | J65: 5:00pm | K65: 1:15 | L65: 214.5 | M65: 2 | N65: 8 | O65: Recreational | Rec Girls | P65: Recreational -- Girls Wings | Q65: Yes | R65: OK - summer session
B66: Summer 2026 Red Wings Intensive/flex drop-in M 3:45p - 6 Weeks | C66: Recreational | D66: Rec Girls | E66: Girls G1 | F66: 2026 Summer Intensive | G66: Active | H66: Niamh M., MAG A. | I66: M | J66: 3:45pm | K66: 1:15 | L66: 214.5 | M66: 2 | N66: 8 | O66: Recreational | Rec Girls | P66: Recreational -- Girls Wings | Q66: Yes | R66: OK - summer session
B67: Kinder White Wings/Intermediate Waitlist (Coach recommendation only - not displayed on website) | C67: Recreational | D67: Rec Girls | E67: Girls G2 | F67: 2026-27 Rec | G67: Active | L67: 0 | M67: 0 | N67: 0 | O67: Recreational | Rec Girls | P67: Recreational -- Girls Wings | Q67: No | R67: NO TUITION
B68: Kinder White/Intermediate F 4:00p | C68: Recreational | D68: Rec Girls | E68: Girls G2 | F68: 2026-27 Rec | G68: Active | H68: Faith F., MAG A. | I68: F | J68: 4:00pm | K68: 1:30 | L68: 167 | M68: 4 | N68: 8 | O68: Recreational | Rec Girls | P68: Recreational -- Girls Wings | Q68: Yes | R68: OK
B69: Kinder White/Intermediate Th 5:00p | C69: Recreational | D69: Rec Girls | E69: Girls G2 | F69: 2026-27 Rec | G69: Active | H69: Claire S., MAG A. | I69: Th | J69: 5:00pm | K69: 1:30 | L69: 167 | M69: 2 | N69: 8 | O69: Recreational | Rec Girls | P69: Recreational -- Girls Wings | Q69: Yes | R69: OK
B70: Summer 2026 White Wings Intensive T 5:15p - 6 weeks | C70: Recreational | D70: Rec Girls | E70: Girls G2 | F70: 2026 Summer Intensive | G70: Active | H70: Riley C., MAG A. | I70: Tu | J70: 5:15pm | K70: 1:30 | L70: 250.5 | M70: 4 | N70: 5 | O70: Recreational | Rec Girls | P70: Recreational -- Girls Wings | Q70: Yes | R70: OK - summer session
B71: Summer 2026 White Wings Intensive W 6:30p - 6 weeks | C71: Recreational | D71: Rec Girls | E71: Girls G2 | F71: 2026 Summer Intensive | G71: Active | H71: Mila T., MAG A. | I71: W | J71: 6:30pm | K71: 1:30 | L71: 250.5 | M71: 1 | N71: 8 | O71: Recreational | Rec Girls | P71: Recreational -- Girls Wings | Q71: Yes | R71: OK - summer session
B72: White Wings/Intermediate F 3:45p | C72: Recreational | D72: Rec Girls | E72: Girls G2 | F72: 2026-27 Rec | G72: Active | H72: Kjeld N., MAG A. | I72: F | J72: 3:45pm | K72: 1:30 | L72: 167 | M72: 5 | N72: 8 | O72: Recreational | Rec Girls | P72: Recreational -- Girls Wings | Q72: Yes | R72: OK
B73: White Wings/Intermediate F 5:30p | C73: Recreational | D73: Rec Girls | E73: Girls G2 | F73: 2026-27 Rec | G73: Active | H73: Mila T., MAG A. | I73: F | J73: 5:30pm | K73: 1:30 | L73: 167 | M73: 7 | N73: 8 | O73: Recreational | Rec Girls | P73: Recreational -- Girls Wings | Q73: Yes | R73: OK
B74: White Wings/Intermediate M 3:45p | C74: Recreational | D74: Rec Girls | E74: Girls G2 | F74: 2026-27 Rec | G74: Active | H74: Kjeld N., MAG A., Mila T. | I74: M | J74: 3:45pm | K74: 1:30 | L74: 167 | M74: 8 | N74: 8 | O74: Recreational | Rec Girls | P74: Recreational -- Girls Wings | Q74: Yes | R74: OK
B75: White Wings/Intermediate M 3:45p* | C75: Recreational | D75: Rec Girls | E75: Girls G2 | F75: 2026-27 Rec | G75: Active | H75: Mila T., Kjeld N., MAG A. | I75: M | J75: 3:45pm | K75: 1:30 | L75: 167 | M75: 8 | N75: 8 | O75: Recreational | Rec Girls | P75: Recreational -- Girls Wings | Q75: Yes | R75: OK
B76: White Wings/Intermediate M 5:00p | C76: Recreational | D76: Rec Girls | E76: Girls G2 | F76: 2026-27 Rec | G76: Active | H76: Abram K., Kjeld N., MAG A. | I76: M | J76: 5:00pm | K76: 1:30 | L76: 167 | M76: 6 | N76: 8 | O76: Recreational | Rec Girls | P76: Recreational -- Girls Wings | Q76: Yes | R76: OK
B77: White Wings/Intermediate M 5:00p* | C77: Recreational | D77: Rec Girls | E77: Girls G2 | F77: 2026-27 Rec | G77: Active | H77: Kjeld N., Abram K., MAG A. | I77: M | J77: 5:00pm | K77: 1:30 | L77: 167 | M77: 5 | N77: 8 | O77: Recreational | Rec Girls | P77: Recreational -- Girls Wings | Q77: Yes | R77: OK
B78: White Wings/Intermediate M 6:30p | C78: Recreational | D78: Rec Girls | E78: Girls G2 | F78: 2026-27 Rec | G78: Active | H78: Mila T., MAG A. | I78: M | J78: 6:30pm | K78: 1:30 | L78: 167 | M78: 7 | N78: 8 | O78: Recreational | Rec Girls | P78: Recreational -- Girls Wings | Q78: Yes | R78: OK
B79: White Wings/Intermediate S 1:00p starts 9/12 | C79: Recreational | D79: Rec Girls | E79: Girls G2 | F79: 2026-27 Rec | G79: Active | H79: Claire S., MAG A. | I79: Sa | J79: 1:00pm | K79: 1:30 | L79: 167 | M79: 8 | N79: 8 | O79: Recreational | Rec Girls | P79: Recreational -- Girls Wings | Q79: Yes | R79: OK
... B91: White Wings/Intermediate W 6:30p | C91: Recreational | D91: Rec Girls | E91: Girls G2 | F91: 2026-27 Rec | G91: Active | H91: Kaylee H., MAG A. | I91: W | J91: 6:30pm | K91: 1:30 | L91: 167 | M91: 1 | N91: 8 | O91: Recreational | Rec Girls | P91: Recreational -- Girls Wings | Q91: Yes | R91: OK
B92: White Wings/Intermediate Waitlist-Level Adjustment | C92: Recreational | D92: Rec Girls | E92: Girls G2 | F92: 2026-27 Rec | G92: Active | K92: 1:30 | L92: 0 | M92: 0 | N92: 0 | O92: Recreational | Rec Girls | P92: Recreational -- Girls Wings | Q92: No | R92: NO TUITION
B93: Blue Wings/Advanced F 5:30p | C93: Recreational | D93: Rec Girls | E93: Girls G3 | F93: 2026-27 Rec | G93: Active | H93: Faith F., Teall (Gentile) D., MAG A. | I93: F | J93: 5:30pm | K93: 1:45 | L93: 184 | M93: 7 | N93: 8 | O93: Recreational | Rec Girls | P93: Recreational -- Girls Wings | Q93: Yes | R93: OK
B94: Blue Wings/Advanced F 5:30p* | C94: Recreational | D94: Rec Girls | E94: Girls G3 | F94: 2026-27 Rec | G94: Active | H94: Teall (Gentile) D., Faith F., MAG A. | I94: F | J94: 5:30pm | K94: 1:45 | L94: 184 | M94: 8 | N94: 8 | O94: Recreational | Rec Girls | P94: Recreational -- Girls Wings | Q94: Yes | R94: OK
B95: Blue Wings/Advanced M 3:30p | C95: Recreational | D95: Rec Girls | E95: Girls G3 | F95: 2026-27 Rec | G95: Active | H95: Bethany W., MAG A. | I95: M | J95: 3:30pm | K95: 1:45 | L95: 184 | M95: 5 | N95: 8 | O95: Recreational | Rec Girls | P95: Recreational -- Girls Wings | Q95: Yes | R95: OK
B96: Blue Wings/Advanced M 5:00p | C96: Recreational | D96: Rec Girls | E96: Girls G3 | F96: 2026-27 Rec | G96: Active | H96: Faith F., MAG A. | I96: M | J96: 5:00pm | K96: 1:45 | L96: 184 | M96: 7 | N96: 8 | O96: Recreational | Rec Girls | P96: Recreational -- Girls Wings | Q96: Yes | R96: OK
B97: Blue Wings/Advanced M 6:30p | C97: Recreational | D97: Rec Girls | E97: Girls G3 | F97: 2026-27 Rec | G97: Active | H97: Kjeld N., MAG A. | I97: M | J97: 6:30pm | K97: 1:45 | L97: 184 | M97: 6 | N97: 8 | O97: Recreational | Rec Girls | P97: Recreational -- Girls Wings | Q97: Yes | R97: OK
B98: Blue Wings/Advanced S11:45a Start 9/12 | C98: Recreational | D98: Rec Girls | E98: Girls G3 | F98: 2026-27 Rec | G98: Active | H98: , MAG A. | I98: Sa | J98: 11:45am | K98: 1:45 | L98: 184 | M98: 6 | N98: 8 | O98: Recreational | Rec Girls | P98: Recreational -- Girls Wings | Q98: Yes | R98: OK
B99: Blue Wings/Advanced Su 2:15p Starts 9/13 | C99: Recreational | D99: Rec Girls | E99: Girls G3 | F99: 2026-27 Rec | G99: Active | H99: Zevon D., Nyx W., MAG A. | I99: Su | J99: 2:15pm | K99: 1:45 | L99: 184 | M99: 3 | N99: 8 | O99: Recreational | Rec Girls | P99: Recreational -- Girls Wings | Q99: Yes | R99: OK
B100: Blue Wings/Advanced Su 2:15p* Starts 9/13 | C100: Recreational | D100: Rec Girls | E100: Girls G3 | F100: 2026-27 Rec | G100: Active | H100: Nyx W., Zevon D., MAG A. | I100: Su | J100: 2:15pm | K100: 1:45 | L100: 184 | M100: 5 | N100: 8 | O100: Recreational | Rec Girls | P100: Recreational -- Girls Wings | Q100: Yes | R100: OK
B101: Blue Wings/Advanced T 5:15p | C101: Recreational | D101: Rec Girls | E101: Girls G3 | F101: 2026-27 Rec | G101: Active | H101: Joelle R., MAG A. | I101: Tu | J101: 5:15pm | K101: 1:45 | L101: 184 | M101: 7 | N101: 8 | O101: Recreational | Rec Girls | P101: Recreational -- Girls Wings | Q101: Yes | R101: OK
B102: Blue Wings/Advanced Th 3:45p | C102: Recreational | D102: Rec Girls | E102: Girls G3 | F102: 2026-27 Rec | G102: Active | H102: Faith F., MAG A. | I102: Th | J102: 3:45pm | K102: 1:45 | L102: 184 | M102: 4 | N102: 8 | O102: Recreational | Rec Girls | P102: Recreational -- Girls Wings | Q102: Yes | R102: OK
B103: Blue Wings/Advanced Th 5:00p | C103: Recreational | D103: Rec Girls | E103: Girls G3 | F103: 2026-27 Rec | G103: Active | H103: Riley C., MAG A. | I103: Th | J103: 5:00pm | K103: 1:45 | L103: 184 | M103: 6 | N103: 8 | O103: Recreational | Rec Girls | P103: Recreational -- Girls Wings | Q103: Yes | R103: OK
B104: Blue Wings/Advanced Th 6:30p | C104: Recreational | D104: Rec Girls | E104: Girls G3 | F104: 2026-27 Rec | G104: Active | H104: Claire S., MAG A. | I104: Th | J104: 6:30pm | K104: 1:45 | L104: 184 | M104: 8 | N104: 8 | O104: Recreational | Rec Girls | P104: Recreational -- Girls Wings | Q104: Yes | R104: OK
... B107: Blue Wings/Advanced W 6:30p* | C107: Recreational | D107: Rec Girls | E107: Girls G3 | F107: 2026-27 Rec | G107: Active | H107: Kjeld N., Faith F., MAG A. | I107: W | J107: 6:30pm | K107: 1:45 | L107: 184 | M107: 5 | N107: 8 | O107: Recreational | Rec Girls | P107: Recreational -- Girls Wings | Q107: Yes | R107: OK
B108: Blue Wings/Advanced Waitlist-Level Adjustment | C108: Recreational | D108: Rec Girls | E108: Girls G3 | F108: 2026-27 Rec | G108: Active | L108: 0 | M108: 0 | N108: 0 | O108: Recreational | Rec Girls | P108: Recreational -- Girls Wings | Q108: No | R108: NO TUITION
B109: Summer 2026 Blue Wings Intensive T 5:15p - 6 weeks | C109: Recreational | D109: Rec Girls | E109: Girls G3 | F109: 2026 Summer Intensive | G109: Active | H109: Danica C., MAG A. | I109: Tu | J109: 5:15pm | K109: 1:45 | L109: 276 | M109: 4 | N109: 8 | O109: Recreational | Rec Girls | P109: Recreational -- Girls Wings | Q109: Yes | R109: OK - summer session
B110: Silver Wings/Elite F 3:45p | C110: Recreational | D110: Rec Girls | E110: Girls G4 | F110: 2026-27 Rec | G110: Active | H110: Teall (Gentile) D., MAG A. | I110: F | J110: 3:45pm | K110: 2:00 | L110: 200 | M110: 9 | N110: 8 | O110: Recreational | Rec Girls | P110: Recreational -- Girls Wings | Q110: Yes | R110: OK
B111: Silver Wings/Elite M 5:00p | C111: Recreational | D111: Rec Girls | E111: Girls G4 | F111: 2026-27 Rec | G111: Active | H111: Nicole E., MAG A. | I111: M | J111: 5:00pm | K111: 2:00 | L111: 200 | M111: 7 | N111: 8 | O111: Recreational | Rec Girls | P111: Recreational -- Girls Wings | Q111: Yes | R111: OK
B112: Silver Wings/Elite T 4:30 | C112: Recreational | D112: Rec Girls | E112: Girls G4 | F112: 2026-27 Rec | G112: Active | H112: Amelia K., MAG A. | I112: Tu | J112: 4:30pm | K112: 2:00 | L112: 200 | M112: 6 | N112: 8 | O112: Recreational | Rec Girls | P112: Recreational -- Girls Wings | Q112: Yes | R112: OK
B113: Silver Wings/Elite T 6:30p | C113: Recreational | D113: Rec Girls | E113: Girls G4 | F113: 2026-27 Rec | G113: Active | H113: Kate P., MAG A. | I113: Tu | J113: 6:30pm | K113: 2:00 | L113: 200 | M113: 7 | N113: 8 | O113: Recreational | Rec Girls | P113: Recreational -- Girls Wings | Q113: Yes | R113: OK
B114: Silver Wings/Elite Th 6:30p | C114: Recreational | D114: Rec Girls | E114: Girls G4 | F114: 2026-27 Rec | G114: Active | H114: Zevon D., MAG A. | I114: Th | J114: 6:30pm | K114: 2:00 | L114: 200 | M114: 2 | N114: 8 | O114: Recreational | Rec Girls | P114: Recreational -- Girls Wings | Q114: Yes | R114: OK
B115: Silver Wings/Elite W 6:30p | C115: Recreational | D115: Rec Girls | E115: Girls G4 | F115: 2026-27 Rec | G115: Active | H115: Teall (Gentile) D., MAG A. | I115: W | J115: 6:30pm | K115: 2:00 | L115: 200 | M115: 6 | N115: 8 | O115: Recreational | Rec Girls | P115: Recreational -- Girls Wings | Q115: Yes | R115: OK
...

Sheet Service Summary
B1: Service Summary — live from the Class Export tab
B2: Billable classes only ($0 and staff placeholders excluded from price columns)
B4: Service Row | C4: Classes | D4: Billable classes | E4: Enrolled | F4: Capacity | G4: Fill % | H4: Min monthly | I4: Avg monthly | J4: Max monthly
B5: Recreational -- Preschool (The Jungle) | C5: =COUNTIF('Class Export (mapped)'!$P$5:$P$180,$B5) -> 45 | D5: =COUNTIFS('Class Export (mapped)'!$P$5:$P$180,$B5,'Class Export (mapped)'!$Q$5:$Q$180,"Yes") -> 39 | E5: =SUMIF('Class Export (mapped)'!$P$5:$P$180,$B5,'Class Export (mapped)'!$M$5:$M$180) -> 211 | F5: =SUMIF('Class Export (mapped)'!$P$5:$P$180,$B5,'Class Export (mapped)'!$N$5:$N$180) -> 309 | G5: =IFERROR(E5/F5,0) -> 0.6828479 | H5: =IFERROR(_xlfn.MINIFS('Class Export (mapped)'!$L$5:$L$180,'Class Export (mapped)'!$P$5:$P$180,$B5,'Class Export (mapped)'!$Q$5:$Q$180,"Yes"),0) -> 114 | I5: =IFERROR(AVERAGEIFS('Class Export (mapped)'!$L$5:$L$180,'Class Export (mapped)'!$P$5:$P$180,$B5,'Class Export (mapped)'!$Q$5:$Q$180,"Yes"),0) -> 120.35897 | J5: =IFERROR(_xlfn.MAXIFS('Class Export (mapped)'!$L$5:$L$180,'Class Export (mapped)'!$P$5:$P$180,$B5,'Class Export (mapped)'!$Q$5:$Q$180,"Yes"),0) -> 122
B6: Recreational -- Girls Wings | C6: =COUNTIF('Class Export (mapped)'!$P$5:$P$180,$B6) -> 85 | D6: =COUNTIFS('Class Export (mapped)'!$P$5:$P$180,$B6,'Class Export (mapped)'!$Q$5:$Q$180,"Yes") -> 75 | E6: =SUMIF('Class Export (mapped)'!$P$5:$P$180,$B6,'Class Export (mapped)'!$M$5:$M$180) -> 402 | F6: =SUMIF('Class Export (mapped)'!$P$5:$P$180,$B6,'Class Export (mapped)'!$N$5:$N$180) -> 579 | G6: =IFERROR(E6/F6,0) -> 0.69430052 | H6: =IFERROR(_xlfn.MINIFS('Class Export (mapped)'!$L$5:$L$180,'Class Export (mapped)'!$P$5:$P$180,$B6,'Class Export (mapped)'!$Q$5:$Q$180,"Yes"),0) -> 143 | I6: =IFERROR(AVERAGEIFS('Class Export (mapped)'!$L$5:$L$180,'Class Export (mapped)'!$P$5:$P$180,$B6,'Class Export (mapped)'!$Q$5:$Q$180,"Yes"),0) -> 176.19333 | J6: =IFERROR(_xlfn.MAXIFS('Class Export (mapped)'!$L$5:$L$180,'Class Export (mapped)'!$P$5:$P$180,$B6,'Class Export (mapped)'!$Q$5:$Q$180,"Yes"),0) -> 300
B7: Recreational -- Boys Wings | C7: =COUNTIF('Class Export (mapped)'!$P$5:$P$180,$B7) -> 11 | D7: =COUNTIFS('Class Export (mapped)'!$P$5:$P$180,$B7,'Class Export (mapped)'!$Q$5:$Q$180,"Yes") -> 8 | E7: =SUMIF('Class Export (mapped)'!$P$5:$P$180,$B7,'Class Export (mapped)'!$M$5:$M$180) -> 33 | F7: =SUMIF('Class Export (mapped)'!$P$5:$P$180,$B7,'Class Export (mapped)'!$N$5:$N$180) -> 64 | G7: =IFERROR(E7/F7,0) -> 0.515625 | H7: =IFERROR(_xlfn.MINIFS('Class Export (mapped)'!$L$5:$L$180,'Class Export (mapped)'!$P$5:$P$180,$B7,'Class Export (mapped)'!$Q$5:$Q$180,"Yes"),0) -> 143 | I7: =IFERROR(AVERAGEIFS('Class Export (mapped)'!$L$5:$L$180,'Class Export (mapped)'!$P$5:$P$180,$B7,'Class Export (mapped)'!$Q$5:$Q$180,"Yes"),0) -> 162.4375 | J7: =IFERROR(_xlfn.MAXIFS('Class Export (mapped)'!$L$5:$L$180,'Class Export (mapped)'!$P$5:$P$180,$B7,'Class Export (mapped)'!$Q$5:$Q$180,"Yes"),0) -> 250.5
B8: Recreational -- Tumbling | C8: =COUNTIF('Class Export (mapped)'!$P$5:$P$180,$B8) -> 12 | D8: =COUNTIFS('Class Export (mapped)'!$P$5:$P$180,$B8,'Class Export (mapped)'!$Q$5:$Q$180,"Yes") -> 9 | E8: =SUMIF('Class Export (mapped)'!$P$5:$P$180,$B8,'Class Export (mapped)'!$M$5:$M$180) -> 62 | F8: =SUMIF('Class Export (mapped)'!$P$5:$P$180,$B8,'Class Export (mapped)'!$N$5:$N$180) -> 76 | G8: =IFERROR(E8/F8,0) -> 0.81578947 | H8: =IFERROR(_xlfn.MINIFS('Class Export (mapped)'!$L$5:$L$180,'Class Export (mapped)'!$P$5:$P$180,$B8,'Class Export (mapped)'!$Q$5:$Q$180,"Yes"),0) -> 122 | I8: =IFERROR(AVERAGEIFS('Class Export (mapped)'!$L$5:$L$180,'Class Export (mapped)'!$P$5:$P$180,$B8,'Class Export (mapped)'!$Q$5:$Q$180,"Yes"),0) -> 142.33333 | J8: =IFERROR(_xlfn.MAXIFS('Class Export (mapped)'!$L$5:$L$180,'Class Export (mapped)'!$P$5:$P$180,$B8,'Class Export (mapped)'!$Q$5:$Q$180,"Yes"),0) -> 183
B9: Competitive -- Pre-Team | C9: =COUNTIF('Class Export (mapped)'!$P$5:$P$180,$B9) -> 2 | D9: =COUNTIFS('Class Export (mapped)'!$P$5:$P$180,$B9,'Class Export (mapped)'!$Q$5:$Q$180,"Yes") -> 2 | E9: =SUMIF('Class Export (mapped)'!$P$5:$P$180,$B9,'Class Export (mapped)'!$M$5:$M$180) -> 10 | F9: =SUMIF('Class Export (mapped)'!$P$5:$P$180,$B9,'Class Export (mapped)'!$N$5:$N$180) -> 12 | G9: =IFERROR(E9/F9,0) -> 0.83333333 | H9: =IFERROR(_xlfn.MINIFS('Class Export (mapped)'!$L$5:$L$180,'Class Export (mapped)'!$P$5:$P$180,$B9,'Class Export (mapped)'!$Q$5:$Q$180,"Yes"),0) -> 200 | I9: =IFERROR(AVERAGEIFS('Class Export (mapped)'!$L$5:$L$180,'Class Export (mapped)'!$P$5:$P$180,$B9,'Class Export (mapped)'!$Q$5:$Q$180,"Yes"),0) -> 255 | J9: =IFERROR(_xlfn.MAXIFS('Class Export (mapped)'!$L$5:$L$180,'Class Export (mapped)'!$P$5:$P$180,$B9,'Class Export (mapped)'!$Q$5:$Q$180,"Yes"),0) -> 310
B10: Competitive -- American Flyers Teams | C10: =COUNTIF('Class Export (mapped)'!$P$5:$P$180,$B10) -> 18 | D10: =COUNTIFS('Class Export (mapped)'!$P$5:$P$180,$B10,'Class Export (mapped)'!$Q$5:$Q$180,"Yes") -> 7 | E10: =SUMIF('Class Export (mapped)'!$P$5:$P$180,$B10,'Class Export (mapped)'!$M$5:$M$180) -> 288 | F10: =SUMIF('Class Export (mapped)'!$P$5:$P$180,$B10,'Class Export (mapped)'!$N$5:$N$180) -> 517 | G10: =IFERROR(E10/F10,0) -> 0.55705996 | H10: =IFERROR(_xlfn.MINIFS('Class Export (mapped)'!$L$5:$L$180,'Class Export (mapped)'!$P$5:$P$180,$B10,'Class Export (mapped)'!$Q$5:$Q$180,"Yes"),0) -> 255 | I10: =IFERROR(AVERAGEIFS('Class Export (mapped)'!$L$5:$L$180,'Class Export (mapped)'!$P$5:$P$180,$B10,'Class Export (mapped)'!$Q$5:$Q$180,"Yes"),0) -> 395.42857 | J10: =IFERROR(_xlfn.MAXIFS('Class Export (mapped)'!$L$5:$L$180,'Class Export (mapped)'!$P$5:$P$180,$B10,'Class Export (mapped)'!$Q$5:$Q$180,"Yes"),0) -> 543
B11: EXCLUDE -- Staff placeholder | C11: =COUNTIF('Class Export (mapped)'!$P$5:$P$180,$B11) -> 3 | D11: =COUNTIFS('Class Export (mapped)'!$P$5:$P$180,$B11,'Class Export (mapped)'!$Q$5:$Q$180,"Yes") -> 0 | E11: =SUMIF('Class Export (mapped)'!$P$5:$P$180,$B11,'Class Export (mapped)'!$M$5:$M$180) -> 24 | F11: =SUMIF('Class Export (mapped)'!$P$5:$P$180,$B11,'Class Export (mapped)'!$N$5:$N$180) -> 190 | G11: =IFERROR(E11/F11,0) -> 0.12631579 | H11: =IFERROR(_xlfn.MINIFS('Class Export (mapped)'!$L$5:$L$180,'Class Export (mapped)'!$P$5:$P$180,$B11,'Class Export (mapped)'!$Q$5:$Q$180,"Yes"),0) -> 0 | I11: =IFERROR(AVERAGEIFS('Class Export (mapped)'!$L$5:$L$180,'Class Export (mapped)'!$P$5:$P$180,$B11,'Class Export (mapped)'!$Q$5:$Q$180,"Yes"),0) -> 0 | J11: =IFERROR(_xlfn.MAXIFS('Class Export (mapped)'!$L$5:$L$180,'Class Export (mapped)'!$P$5:$P$180,$B11,'Class Export (mapped)'!$Q$5:$Q$180,"Yes"),0) -> 0
B12: TOTAL (excl. staff placeholders) | C12: =SUM(C5:C10) -> 173 | D12: =SUM(D5:D10) -> 140 | E12: =SUM(E5:E10) -> 1006 | F12: =SUM(F5:F10) -> 1557 | G12: =IFERROR(E12/F12,0) -> 0.64611432
B14: Reading these numbers
B15: Team enrolled counts the 7 billing groups plus the 11 $0 practice/roster groups, so it overstates unique athletes.
B16: Unique team athletes = the 'MAG Team 2026-27' roster (77). Billing-group enrolment totals 74.
B17: Tuition is monthly except the 11 Summer Intensive classes, which are flat 6-week fees.
B18: Source: Jackrabbit Class List export, 176 classes, 28 July 2026. Mapping rules on the Crosswalk tab.

Sheet Crosswalk
B1: Mapping rules applied
B4: Cat1 | C4: Cat2 | D4: Cat3 override | E4: Maps to service row | F4: Classes
B5: Recreational | C5: Pre-School | D5: — | E5: Recreational -- Preschool (The Jungle) | F5: 36
B6: Recreational | C6: Parent-Child | D6: — | E6: Recreational -- Preschool (The Jungle) | F6: 9
B7: Recreational | C7: Rec Girls | D7: — | E7: Recreational -- Girls Wings | F7: 85
B8: Recreational | C8: Rec Boys | D8: — | E8: Recreational -- Boys Wings | F8: 11
B9: Recreational | C9: Tumble (Combined) | D9: — | E9: Recreational -- Tumbling | F9: 12
B10: Recreational | C10: Rec Girls | D10: Girls PT1 | E10: Competitive -- Pre-Team | F10: 1
B11: Recreational | C11: Rec Boys | D11: Boys PT2 | E11: Competitive -- Pre-Team | F11: 1
B12: Team | C12: (blank) | D12: — | E12: Competitive -- American Flyers Teams | F12: 18
B13: Staff | C13: (blank) | D13: — | E13: EXCLUDE -- Staff placeholder | F13: 3
B15: Rows not yet in your nine-row structure:
B16: Ancillary -- Open Gym · Ancillary -- Annual Membership Fees · Events -- American Flyers Cup
B17: None of these are classes, so they do not appear in this export. They live in the transaction sub-types instead.
